maptasker/.DS_Store
maptasker/__init__.py
maptasker/assets/.DS_Store
maptasker/assets/.MapTasker_RunCount.txt
maptasker/assets/.MapTasker_Settings.pkl
maptasker/assets/MapTasker_Settings.toml
maptasker/assets/Thumbs.db
maptasker/assets/bmc-logo-no-background.png
maptasker/assets/color_wheel.png
maptasker/assets/icons/ar.png
maptasker/assets/icons/arrow.png
maptasker/assets/icons/bn.png
maptasker/assets/icons/cs.png
maptasker/assets/icons/da.png
maptasker/assets/icons/de.png
maptasker/assets/icons/el.png
maptasker/assets/icons/en.png
maptasker/assets/icons/en_orig.png
maptasker/assets/icons/en_orig1.png
maptasker/assets/icons/es.png
maptasker/assets/icons/fa.png
maptasker/assets/icons/fi.png
maptasker/assets/icons/fr.png
maptasker/assets/icons/gu.png
maptasker/assets/icons/hi.png
maptasker/assets/icons/in.png
maptasker/assets/icons/it.png
maptasker/assets/icons/ja.png
maptasker/assets/icons/ko.png
maptasker/assets/icons/mr.png
maptasker/assets/icons/nl.png
maptasker/assets/icons/no.png
maptasker/assets/icons/pl.png
maptasker/assets/icons/pt.png
maptasker/assets/icons/ru.png
maptasker/assets/icons/sv.png
maptasker/assets/icons/sw.png
maptasker/assets/icons/ta.png
maptasker/assets/icons/te.png
maptasker/assets/icons/th.png
maptasker/assets/icons/tr.png
maptasker/assets/icons/uk.png
maptasker/assets/icons/ur.png
maptasker/assets/icons/vi.png
maptasker/assets/icons/zh_CN.png
maptasker/assets/icons/zh_TW.png
maptasker/assets/json/.MapTasker_RunCount.txt
maptasker/assets/json/arg_dict.py
maptasker/assets/json/arg_specs.json
maptasker/assets/json/buildit.log
maptasker/assets/json/category_descriptions.json
maptasker/assets/json/task_all_actions.json
maptasker/assets/maptasker_logo_dark.png
maptasker/assets/maptasker_logo_light.png
maptasker/assets/target.png
maptasker/custom_overrides/.DS_Store
maptasker/custom_overrides/MapTasker_Updates.txt
maptasker/custom_overrides/customtkinter/__init__.py
maptasker-10.0.5.dist-info/METADATA
maptasker-10.0.5.dist-info/WHEEL
maptasker-10.0.5.dist-info/entry_points.txt
maptasker-10.0.5.dist-info/licenses/LICENSE
maptasker-10.0.5.dist-info/licenses/LICENSE.txt
maptasker-10.0.5.dist-info/RECORD
