Metadata-Version: 2.4
Name: maptasker
Version: 10.0.5
Summary: Utility to display your entire Android 'Tasker' configuration on your Desktop.
License-Expression: MIT
License-File: LICENSE
License-File: LICENSE.txt
Keywords: tasker,Tasker,map tasker,configuration,tasker configuration
Author: Michael Rubin
Author-email: mikrubin@gmail.com
Requires-Python: >=3.11,<4.0
Classifier: Programming Language :: Python :: 3
Classifier: Programming Language :: Python :: 3.11
Classifier: Programming Language :: Python :: 3.12
Classifier: Programming Language :: Python :: 3.13
Classifier: Programming Language :: Python :: 3.14
Requires-Dist: anthropic (>=0.76.0)
Requires-Dist: cv3 (>=1.3.2,<2.0.0)
Requires-Dist: darkdetect (>=0.8.0)
Requires-Dist: deep_translator (>=1.11.4)
Requires-Dist: defusedxml (>=0.7.1)
Requires-Dist: google-genai (>=1.60.0)
Requires-Dist: ollama (>=0.6.1)
Requires-Dist: openai (>=2.15.0)
Requires-Dist: packaging (>=26.0)
Requires-Dist: pillow (==12.1.0)
Requires-Dist: psutil (>=7.2.1)
Requires-Dist: pytube2 (>=15.0.16,<16.0.0)
Requires-Dist: requests (>=2.32.5)
Requires-Dist: tomli_w (>=1.2.0)
Requires-Dist: webcolors (>=25.10.0)
Requires-Dist: yt-dlp (>=2025.10.22,<2026.0.0)
Project-URL: Bug Tracker, https://github.com/mctinker/Map-Tasker/issues
Project-URL: Changelog, https://github.com/mctinker/Map-Tasker/CHANGELOG.md
Project-URL: Homepage, https://github.com/mctinker/Map-Tasker
